prwm/__init__.py
prwm/common.py
prwm/prwb.py
prwm/prwm.py
prwm-0.0.1.dist-info/METADATA
prwm-0.0.1.dist-info/RECORD
prwm-0.0.1.dist-info/WHEEL
prwm-0.0.1.dist-info/top_level.txt
